plutoplot/__init__.py
plutoplot/coordinates.py
plutoplot/grid.py
plutoplot/info.py
plutoplot/metadata.py
plutoplot/misc.py
plutoplot/plotting.py
plutoplot/plutodata.py
plutoplot/scripts.py
plutoplot/simulation.py
plutoplot-0.3.2.dist-info/entry_points.txt
plutoplot-0.3.2.dist-info/WHEEL
plutoplot-0.3.2.dist-info/METADATA
plutoplot-0.3.2.dist-info/RECORD
