Metadata-Version: 2.1
Name: plutoplot
Version: 0.3.2
Summary: Python package to load PLUTO simulation data
Home-page: https://github.com/Simske/plutoplot
License: GPL-3.0-or-later
Author: Simeon Doetsch
Author-email: science@simske.com
Requires-Python: >=3.7,<3.11
Classifier: Development Status :: 4 - Beta
Classifier: License :: OSI Approved :: GNU General Public License v3 or later (GPLv3+)
Classifier: Programming Language :: Python :: 3
Classifier: Programming Language :: Python :: 3.10
Classifier: Programming Language :: Python :: 3.7
Classifier: Programming Language :: Python :: 3.8
Classifier: Programming Language :: Python :: 3.9
Classifier: Topic :: Scientific/Engineering :: Physics
Provides-Extra: hdf5
Provides-Extra: interactive
Requires-Dist: h5py (>=3.0,<4.0); extra == "hdf5"
Requires-Dist: ipywidgets (>=7.0,<8.0); extra == "interactive"
Requires-Dist: matplotlib (>=3.3,<4.0)
Requires-Dist: numpy (>=1.19,<2.0)
Project-URL: Bug Tracker, https://github.com/Simske/plutoplot/issues
Project-URL: Documentation, https://plutoplot.readthedocs.io
Project-URL: Repository, https://github.com/Simske/plutoplot
